onefile/cli.py
onefile/core.py
onefile/rules.py
onefile/watcher.py
onefile_organizer-0.1.1.dist-info/licenses/LICENSE
onefile_organizer-0.1.1.dist-info/METADATA
onefile_organizer-0.1.1.dist-info/WHEEL
onefile_organizer-0.1.1.dist-info/entry_points.txt
onefile_organizer-0.1.1.dist-info/top_level.txt
onefile_organizer-0.1.1.dist-info/RECORD
