Metadata-Version: 2.4
Name: onefile-organizer
Version: 0.1.1
Summary: Automatically organize your messy folders with smart file sorting
Author-email: Aditya Ranjan <aditya87331@gmail.com>
License: MIT
Project-URL: Homepage, https://github.com/Aditya-Ranjan1234/onefile-organizer
Project-URL: Documentation, https://github.com/Aditya-Ranjan1234/onefile-organizer#readme
Project-URL: Issues, https://github.com/Aditya-Ranjan1234/onefile-organizer/issues
Project-URL: Source, https://github.com/Aditya-Ranjan1234/onefile-organizer
Keywords: file,organization,organizer,automation,productivity
Classifier: Development Status :: 4 - Beta
Classifier: Intended Audience :: End Users/Desktop
Classifier: License :: OSI Approved :: MIT License
Classifier: Programming Language :: Python :: 3
Classifier: Programming Language :: Python :: 3.7
Classifier: Programming Language :: Python :: 3.8
Classifier: Programming Language :: Python :: 3.9
Classifier: Programming Language :: Python :: 3.10
Classifier: Programming Language :: Python :: 3.11
Classifier: Topic :: Desktop Environment
Classifier: Topic :: System :: Filesystems
Classifier: Topic :: Utilities
Classifier: Topic :: Software Development :: Libraries :: Python Modules
License-File: LICENSE
Requires-Dist: typing-extensions>=3.7.4; python_version < "3.8"
Requires-Dist: python-magic; platform_system != "Windows"
Requires-Dist: python-magic-bin; platform_system == "Windows"
Provides-Extra: dev
Requires-Dist: pytest>=6.0; extra == "dev"
Requires-Dist: pytest-cov>=2.0; extra == "dev"
Requires-Dist: black>=22.0; extra == "dev"
Requires-Dist: isort>=5.0; extra == "dev"
Requires-Dist: mypy>=0.900; extra == "dev"
Requires-Dist: flake8>=4.0; extra == "dev"
Requires-Dist: twine>=3.0; extra == "dev"
Dynamic: license-file
